ElasticCollision/.pylintrc
ElasticCollision/__init__.py
ElasticCollision/c_game.cp310-win_amd64.pyd
ElasticCollision/c_game.cp36-win_amd64.pyd
ElasticCollision/c_game.cp37-win_amd64.pyd
ElasticCollision/c_game.cp38-win_amd64.pyd
ElasticCollision/c_game.cp39-win_amd64.pyd
ElasticCollision/ec_game.cp310-win_amd64.pyd
ElasticCollision/ec_game.cp36-win_amd64.pyd
ElasticCollision/ec_game.cp37-win_amd64.pyd
ElasticCollision/ec_game.cp38-win_amd64.pyd
ElasticCollision/ec_game.cp39-win_amd64.pyd
ElasticCollision/ec_real.cp310-win_amd64.pyd
ElasticCollision/ec_real.cp36-win_amd64.pyd
ElasticCollision/ec_real.cp37-win_amd64.pyd
ElasticCollision/ec_real.cp38-win_amd64.pyd
ElasticCollision/ec_real.cp39-win_amd64.pyd
ElasticCollision/Assets/GameDomain.PNG
ElasticCollision/Assets/GameDomain_wrong_trajectory.PNG
ElasticCollision/Assets/RealDomain.PNG
ElasticCollision/Assets/math1.png
ElasticCollision/Assets/math2.png
ElasticCollision/Assets/math3.png
ElasticCollision/Assets/math4.png
ElasticCollision/Source/elastic_collision.c
ElasticCollision/Source/vector.c
ElasticCollision/__pycache__/__init__.cpython-37.pyc
ElasticCollision/game/__init__.py
ElasticCollision/game/c_game.c
ElasticCollision/game/c_game.pyx
ElasticCollision/game/ec_game.c
ElasticCollision/game/ec_game.pyx
ElasticCollision/game/setup_ec_game.py
ElasticCollision/real/__init__.py
ElasticCollision/real/ec_real.c
ElasticCollision/real/ec_real.pyx
ElasticCollision/real/setup_ec_real.py
ElasticCollision/tests/__init__.py
ElasticCollision/tests/test_ec_game.py
ElasticCollision/tests/test_ec_real.py
ElasticCollision-1.0.5.data/data/lib/site-packages/ElasticCollision/LICENSE
ElasticCollision-1.0.5.data/data/lib/site-packages/ElasticCollision/MANIFEST.in
ElasticCollision-1.0.5.data/data/lib/site-packages/ElasticCollision/README.md
ElasticCollision-1.0.5.data/data/lib/site-packages/ElasticCollision/pyproject.toml
ElasticCollision-1.0.5.dist-info/METADATA
ElasticCollision-1.0.5.dist-info/RECORD
ElasticCollision-1.0.5.dist-info/WHEEL
ElasticCollision-1.0.5.dist-info/top_level.txt
