Metadata-Version: 2.1
Name: ElasticCollision
Version: 1.0.5
Summary: ElasticCollision tools for pygame and arcade games 
Home-page: https://github.com/yoyoberenguer/ElasticCollision
Author: Yoann Berenguer
Author-email: yoyoberenguer@hotmail.com
License: MIT
Project-URL: Bug Reports, https://github.com/yoyoberenguer/ElasticCollision/issues
Project-URL: Source, https://github.com/yoyoberenguer/ElasticCollision
Platform: any
Classifier: Development Status :: 4 - Beta
Classifier: Intended Audience :: Developers
Classifier: Topic :: Software Development :: Build Tools
Classifier: Operating System :: Microsoft :: Windows
Classifier: Programming Language :: Python
Classifier: Programming Language :: Cython
Classifier: License :: OSI Approved :: MIT License
Classifier: Programming Language :: Python :: 3.6
Classifier: Programming Language :: Python :: 3.7
Classifier: Programming Language :: Python :: 3.8
Classifier: Programming Language :: Python :: 3.9
Classifier: Programming Language :: Python :: 3.10
Classifier: Topic :: Software Development :: Libraries :: Python Modules
Requires-Python: >=3.6
License-File: LICENSE
Requires-Dist: setuptools (>=49.2.1)
Requires-Dist: Cython (>=0.28)
Requires-Dist: numpy (>=1.18)
Requires-Dist: pygame (>=2.0)
